setup.py
gaussian_and_binomial_mykel/Binomialdistribution.py
gaussian_and_binomial_mykel/Gaussiandistribution.py
gaussian_and_binomial_mykel/Generaldistribution.py
gaussian_and_binomial_mykel/__init__.py
gaussian_and_binomial_mykel.egg-info/PKG-INFO
gaussian_and_binomial_mykel.egg-info/SOURCES.txt
gaussian_and_binomial_mykel.egg-info/dependency_links.txt
gaussian_and_binomial_mykel.egg-info/not-zip-safe
gaussian_and_binomial_mykel.egg-info/top_level.txt