Metadata-Version: 1.0
Name: gaussian-and-binomial-mykel
Version: 0.1
Summary: Package for calculating Gaussian and Binomial distributions
Home-page: UNKNOWN
Author: Michael Eze
Author-email: UNKNOWN
License: UNKNOWN
Platform: UNKNOWN
